autotuning_methodology/__init__.py
autotuning_methodology/baseline.py
autotuning_methodology/caching.py
autotuning_methodology/curves.py
autotuning_methodology/experiments.py
autotuning_methodology/experiments_defaults.json
autotuning_methodology/formats_interface.py
autotuning_methodology/report_experiments.py
autotuning_methodology/runner.py
autotuning_methodology/searchspace_statistics.py
autotuning_methodology/validators.py
autotuning_methodology/visualize_experiments.py
autotuning_methodology/schemas/T4.json
autotuning_methodology/schemas/experiments.json
autotuning_methodology-1.1.0.dist-info/entry_points.txt
autotuning_methodology-1.1.0.dist-info/licenses/LICENSE
autotuning_methodology-1.1.0.dist-info/WHEEL
autotuning_methodology-1.1.0.dist-info/METADATA
autotuning_methodology-1.1.0.dist-info/RECORD
