Metadata-Version: 2.4
Name: autotuning_methodology
Version: 1.1.0
Summary: Software package easing implementation of the guidelines of the 2024 paper 'A Methodology for Comparing Auto-Tuning Optimization Algorithms' (https://doi.org/10.1016/j.future.2024.05.021). The DOI of this software is https://doi.org/10.5281/zenodo.11243974.
Keywords: autotuning,auto-tuning,methodology,scientific
Author-email: Floris-Jan Willemsen <fjwillemsen97@gmail.com>
Requires-Python: >=3.10,<4
Classifier: Development Status :: 5 - Production/Stable
Classifier: License :: OSI Approved :: MIT License
Classifier: Natural Language :: English
Classifier: Operating System :: OS Independent
Classifier: Programming Language :: Python :: 3.10
Classifier: Programming Language :: Python :: 3.11
Classifier: Programming Language :: Python :: 3.12
Classifier: Programming Language :: Python :: 3.13
License-File: LICENSE
Requires-Dist: numpy (>=2.0.0)
Requires-Dist: scipy >= 1.10.1
Requires-Dist: scikit-learn >= 1.0.2
Requires-Dist: matplotlib >= 3.7.1
Requires-Dist: yappi >= 1.4.0
Requires-Dist: progressbar2 >= 4.2.0
Requires-Dist: jsonschema >= 4.17.3
Requires-Dist: nonconformist >= 2.1.0
Requires-Dist: kernel_tuner >= 1.3.0
Requires-Dist: pylint >=2.14.4 ; extra == "dev"
Requires-Dist: black >= 23.3.0 ; extra == "dev"
Requires-Dist: sphinx >= 7.2.1 ; extra == "docs"
Requires-Dist: sphinx_rtd_theme >= 2.0.0 ; extra == "docs"
Requires-Dist: sphinx-pyproject >= 0.3.0 ; extra == "docs"
Requires-Dist: ruff >= 0.0.263 ; extra == "test"
Requires-Dist: pep440 >= 0.1.2 ; extra == "test"
Requires-Dist: pytest >= 7.3.1 ; extra == "test"
Requires-Dist: pytest-cov >= 4.0.0 ; extra == "test"
Requires-Dist: nox >= 2023.4.22 ; extra == "test"
Requires-Dist: crepes >= 0.2.0 ; extra == "test"
Requires-Dist: tomli >= 2.0.1 ; extra == "test"
Project-URL: Bug Tracker, https://github.com/fjwillemsen/autotuning_methodology/issues
Project-URL: Documentation, https://fjwillemsen.github.io/autotuning_methodology/
Project-URL: Repository, https://github.com/fjwillemsen/autotuning_methodology
Provides-Extra: dev
Provides-Extra: docs
Provides-Extra: test
